yodel/__init__.py
yodel/classes.py
yodel/config.py
yodel/dynamicheaders.py
yodel/globaldat.py
yodel/receiver.py
yodel/sender.py
yodel/standardformats.py
yodel/yodel.py
yodel/yodelmain.py
yodelnet-0.1.0.dist-info/LICENSE
yodelnet-0.1.0.dist-info/METADATA
yodelnet-0.1.0.dist-info/WHEEL
yodelnet-0.1.0.dist-info/top_level.txt
yodelnet-0.1.0.dist-info/RECORD
