Metadata-Version: 2.1
Name: yodelnet
Version: 0.1.0
Summary: Yodel is a python library that uses WIFI hardware for remote control purposes
Home-page: https://github.com/aldenq/Yodel
Author: Alden Quigley
Author-email: aldenaquigley@gmail.com
License: UNKNOWN
Platform: UNKNOWN
Classifier: Programming Language :: Python :: 3
Classifier: License :: OSI Approved :: MIT License
Classifier: Operating System :: POSIX :: Linux
Requires-Python: >=3.6
